edwh_files_plugin/__about__.py
edwh_files_plugin/__init__.py
edwh_files_plugin/compression.py
edwh_files_plugin/files_plugin.py
edwh_files_plugin-1.2.0.dist-info/METADATA
edwh_files_plugin-1.2.0.dist-info/WHEEL
edwh_files_plugin-1.2.0.dist-info/entry_points.txt
edwh_files_plugin-1.2.0.dist-info/RECORD
