Metadata-Version: 2.3
Name: edwh-files-plugin
Version: 1.2.0
Summary: `edwh` plugin for files.edwh.nl
Project-URL: Documentation, https://github.com/educationwarehouse/edwh-files-plugin#readme
Project-URL: Issues, https://github.com/educationwarehouse/edwh-files-plugin/issues
Project-URL: Source, https://github.com/educationwarehouse/edwh-files-plugin
Author-email: Remco Boerma <remco.b@educationwarehouse.nl>, Robin van der Noord <robin.vdn@educationwarehouse.nl>
Classifier: Development Status :: 4 - Beta
Classifier: Programming Language :: Python
Classifier: Programming Language :: Python :: 3.10
Classifier: Programming Language :: Python :: 3.11
Classifier: Programming Language :: Python :: 3.12
Classifier: Programming Language :: Python :: Implementation :: CPython
Classifier: Programming Language :: Python :: Implementation :: PyPy
Requires-Python: >=3.10
Requires-Dist: progress
Requires-Dist: requests
Requires-Dist: requests-toolbelt
Requires-Dist: rich
Requires-Dist: threadful
Provides-Extra: dev
Requires-Dist: black; extra == 'dev'
Requires-Dist: edwh; extra == 'dev'
Requires-Dist: hatch; extra == 'dev'
Requires-Dist: pytest; extra == 'dev'
Requires-Dist: pytest-coverage; extra == 'dev'
